logforge/__about__.py
logforge/__init__.py
logforge/cli.py
logforge/core/config.py
logforge/core/formats.py
logforge/core/generator.py
logforge/generators/__init__.py
logforge/generators/anomalies.py
logforge/generators/data.py
logforge/utils/__init__.py
logforge/utils/performance.py
logforge-1.0.0.dist-info/METADATA
logforge-1.0.0.dist-info/WHEEL
logforge-1.0.0.dist-info/entry_points.txt
logforge-1.0.0.dist-info/licenses/LICENSE
logforge-1.0.0.dist-info/RECORD
