Metadata-Version: 2.4
Name: logforge
Version: 1.0.0
Summary: A high-performance, professional-grade log generator for testing, simulation, and development
Project-URL: Homepage, https://github.com/josesolisrosales/logforge
Project-URL: Repository, https://github.com/josesolisrosales/logforge
Project-URL: Issues, https://github.com/josesolisrosales/logforge/issues
Project-URL: Documentation, https://github.com/josesolisrosales/logforge#readme
Author-email: Jose Solis <jose.solisrosales@gmail.com>
License: MIT License
License-File: LICENSE
Keywords: log-generator,logging,performance,simulation,testing
Classifier: Intended Audience :: Developers
Classifier: Intended Audience :: System Administrators
Classifier: License :: OSI Approved :: MIT License
Classifier: Operating System :: OS Independent
Classifier: Programming Language :: Python :: 3.12
Classifier: Topic :: Software Development :: Testing
Classifier: Topic :: System :: Logging
Classifier: Topic :: System :: Systems Administration
Requires-Python: >=3.12
Requires-Dist: click>=8.0.0
Requires-Dist: faker>=18.0.0
Requires-Dist: numpy>=1.24.0
Requires-Dist: orjson>=3.9.0
Requires-Dist: psutil>=5.9.0
Requires-Dist: pydantic>=2.0.0
Requires-Dist: rich>=13.0.0
Provides-Extra: dev
Requires-Dist: black>=23.0.0; extra == 'dev'
Requires-Dist: flake8>=6.0.0; extra == 'dev'
Requires-Dist: isort>=5.12.0; extra == 'dev'
Requires-Dist: mypy>=1.5.0; extra == 'dev'
Requires-Dist: pre-commit>=3.0.0; extra == 'dev'
Requires-Dist: pytest-cov>=4.0.0; extra == 'dev'
Requires-Dist: pytest>=7.0.0; extra == 'dev'
Provides-Extra: docs
Requires-Dist: mkdocs-click>=0.8.0; extra == 'docs'
Requires-Dist: mkdocs-material>=9.0.0; extra == 'docs'
Requires-Dist: mkdocs>=1.5.0; extra == 'docs'
Provides-Extra: performance
Requires-Dist: memory-profiler>=0.60.0; extra == 'performance'
Requires-Dist: psutil>=5.9.0; extra == 'performance'
